myclang/__init__.py
myclang/__version__.py
myclang/astgen.py
myclang/betterenums.py
myclang/build_meta.py
myclang/cindex.py
myclang/constants.py
myclang/enumerations.py
myclang/global_cfg.py
myclang/ops.py
myclang/resource.py
myclang/cext/__init__.py
myclang/cext/clangutils.cc
myclang/cext/clangutils.pyd
myclang/cext/clcompiler.cc
myclang/cext/clcompiler.pyd
myclang/cext/libclang.json
myclang/cext/myclang.dll
myclang/cext/myclang.lib
myclang/cext/include/compiler.h
myclang/cext/libclang/ARCMigrate.cpp
myclang/cext/libclang/BuildSystem.cpp
myclang/cext/libclang/CIndex.cpp
myclang/cext/libclang/CIndexCXX.cpp
myclang/cext/libclang/CIndexCodeCompletion.cpp
myclang/cext/libclang/CIndexCustom.cpp
myclang/cext/libclang/CIndexDiagnostic.cpp
myclang/cext/libclang/CIndexDiagnostic.h
myclang/cext/libclang/CIndexHigh.cpp
myclang/cext/libclang/CIndexInclusionStack.cpp
myclang/cext/libclang/CIndexUSRs.cpp
myclang/cext/libclang/CIndexer.cpp
myclang/cext/libclang/CIndexer.h
myclang/cext/libclang/CLog.h
myclang/cext/libclang/CXComment.cpp
myclang/cext/libclang/CXComment.h
myclang/cext/libclang/CXCompilationDatabase.cpp
myclang/cext/libclang/CXCursor.cpp
myclang/cext/libclang/CXCursor.h
myclang/cext/libclang/CXIndexDataConsumer.cpp
myclang/cext/libclang/CXIndexDataConsumer.h
myclang/cext/libclang/CXLoadedDiagnostic.cpp
myclang/cext/libclang/CXLoadedDiagnostic.h
myclang/cext/libclang/CXSourceLocation.cpp
myclang/cext/libclang/CXSourceLocation.h
myclang/cext/libclang/CXStoredDiagnostic.cpp
myclang/cext/libclang/CXString.cpp
myclang/cext/libclang/CXString.h
myclang/cext/libclang/CXTranslationUnit.h
myclang/cext/libclang/CXType.cpp
myclang/cext/libclang/CXType.h
myclang/cext/libclang/CursorVisitor.h
myclang/cext/libclang/DeclKindToCXCursor.cpp
myclang/cext/libclang/DeclKindToCXCursor.h
myclang/cext/libclang/FatalErrorHandler.cpp
myclang/cext/libclang/IndexCustom.h
myclang/cext/libclang/Index_Internal.h
myclang/cext/libclang/Indexing.cpp
myclang/cext/libclang/cc1_main.cpp
myclang-0.1.3.dist-info/LICENSE
myclang-0.1.3.dist-info/METADATA
myclang-0.1.3.dist-info/WHEEL
myclang-0.1.3.dist-info/entry_points.txt
myclang-0.1.3.dist-info/top_level.txt
myclang-0.1.3.dist-info/RECORD
