Metadata-Version: 2.1
Name: myclang
Version: 0.1.3
Summary: standalone libclang code with some modifications
Home-page: https://github.com/FindDefinition/myclang
Author: Yan Yan
Author-email: yanyan.sub@outlook.com
License: MIT
Platform: UNKNOWN
Classifier: License :: OSI Approved :: MIT License
Classifier: Programming Language :: Python
Classifier: Programming Language :: Python :: 3
Classifier: Programming Language :: Python :: Implementation :: CPython
Requires-Python: >=3.5
Requires-Dist: ccimport (>=0.1.11)
